annotationtools/__init__.py
annotationtools/cvat.py
annotationtools/dataset.py
annotationtools-0.2.0.dist-info/METADATA
annotationtools-0.2.0.dist-info/WHEEL
annotationtools-0.2.0.dist-info/licenses/LICENSE
annotationtools-0.2.0.dist-info/RECORD
